sincpro_payments_sdk/__init__.py
sincpro_payments_sdk/apps/__init__.py
sincpro_payments_sdk/apps/common/__init__.py
sincpro_payments_sdk/apps/common/domain/__init__.py
sincpro_payments_sdk/apps/common/domain/payments.py
sincpro_payments_sdk/apps/cybersource/__init__.py
sincpro_payments_sdk/apps/cybersource/adapters/__init__.py
sincpro_payments_sdk/apps/cybersource/adapters/cybersource_rest_api/__init__.py
sincpro_payments_sdk/apps/cybersource/adapters/cybersource_rest_api/common.py
sincpro_payments_sdk/apps/cybersource/adapters/cybersource_rest_api/payer_auth_adapter.py
sincpro_payments_sdk/apps/cybersource/adapters/cybersource_rest_api/payment_adapter.py
sincpro_payments_sdk/apps/cybersource/adapters/cybersource_rest_api/tokenization_adapter.py
sincpro_payments_sdk/apps/cybersource/domain/__init__.py
sincpro_payments_sdk/apps/cybersource/domain/card.py
sincpro_payments_sdk/apps/cybersource/domain/country_codes.py
sincpro_payments_sdk/apps/cybersource/domain/credentials.py
sincpro_payments_sdk/apps/cybersource/domain/customer.py
sincpro_payments_sdk/apps/cybersource/domain/payments.py
sincpro_payments_sdk/apps/cybersource/infrastructure/__init__.py
sincpro_payments_sdk/apps/cybersource/infrastructure/dependencies.py
sincpro_payments_sdk/apps/cybersource/infrastructure/framework.py
sincpro_payments_sdk/apps/cybersource/services/__init__.py
sincpro_payments_sdk/apps/cybersource/services/cancel_or_refund/__init__.py
sincpro_payments_sdk/apps/cybersource/services/cancel_or_refund/cancel.py
sincpro_payments_sdk/apps/cybersource/services/pay_new_card/__init__.py
sincpro_payments_sdk/apps/cybersource/services/pay_new_card/enrollment.py
sincpro_payments_sdk/apps/cybersource/services/pay_new_card/validation.py
sincpro_payments_sdk/apps/cybersource/services/pay_saved_card/__init__.py
sincpro_payments_sdk/apps/cybersource/services/pay_saved_card/enrollment.py
sincpro_payments_sdk/apps/cybersource/services/pay_saved_card/validation.py
sincpro_payments_sdk-4.1.0.dist-info/METADATA
sincpro_payments_sdk-4.1.0.dist-info/WHEEL
sincpro_payments_sdk-4.1.0.dist-info/licenses/LICENSE.md
sincpro_payments_sdk-4.1.0.dist-info/RECORD
