Metadata-Version: 2.4
Name: sincpro-payments-sdk
Version: 4.1.0
Summary: Agnostic SDK for payments like cybersource, Paypal and local payments
License: Sincpro S.R.L.
License-File: LICENSE.md
Author: Gutierrez, Andres
Author-email: andru1236@gmail.com
Requires-Python: >=3.12,<4.0
Classifier: License :: Other/Proprietary License
Classifier: Programming Language :: Python :: 3
Classifier: Programming Language :: Python :: 3.12
Classifier: Programming Language :: Python :: 3.13
Classifier: Programming Language :: Python :: 3.14
Requires-Dist: pydantic (>=2.12.5,<3.0.0)
Requires-Dist: requests (>=2.32.5,<3.0.0)
Requires-Dist: sincpro-framework (>=3.0.6,<4.0.0)
Project-URL: Documentation, https://www.notion.so/sincpro/
Project-URL: Homepage, https://github.com/Sincpro-SRL/sincpro_payments_sdk/
Project-URL: Repository, https://github.com/Sincpro-SRL/sincpro_payments_sdk/
